avocado_varianter_cit/Cit.py
avocado_varianter_cit/CombinationMatrix.py
avocado_varianter_cit/CombinationRow.py
avocado_varianter_cit/Parser.py
avocado_varianter_cit/Solver.py
avocado_varianter_cit/varianter_cit.py
avocado_framework_plugin_varianter_cit-113.0.dist-info/METADATA
avocado_framework_plugin_varianter_cit-113.0.dist-info/WHEEL
avocado_framework_plugin_varianter_cit-113.0.dist-info/entry_points.txt
avocado_framework_plugin_varianter_cit-113.0.dist-info/top_level.txt
avocado_framework_plugin_varianter_cit-113.0.dist-info/RECORD
